formance/__init__.py
formance/accounts.py
formance/balances.py
formance/clients.py
formance/ledger.py
formance/logs.py
formance/mapping.py
formance/orchestration.py
formance/payments.py
formance/scopes.py
formance/script.py
formance/sdk.py
formance/search.py
formance/server.py
formance/stats.py
formance/transactions.py
formance/users.py
formance/wallets.py
formance/webhooks.py
formance/models/__init__.py
formance/models/operations/__init__.py
formance/models/operations/activateconfig.py
formance/models/operations/addmetadataontransaction.py
formance/models/operations/addmetadatatoaccount.py
formance/models/operations/addscopetoclient.py
formance/models/operations/addtransientscope.py
formance/models/operations/changeconfigsecret.py
formance/models/operations/confirmhold.py
formance/models/operations/connectorsstripetransfer.py
formance/models/operations/countaccounts.py
formance/models/operations/counttransactions.py
formance/models/operations/createbalance.py
formance/models/operations/createclient.py
formance/models/operations/createscope.py
formance/models/operations/createsecret.py
formance/models/operations/createtransaction.py
formance/models/operations/createtransactions.py
formance/models/operations/createwallet.py
formance/models/operations/createworkflow.py
formance/models/operations/creditwallet.py
formance/models/operations/deactivateconfig.py
formance/models/operations/debitwallet.py
formance/models/operations/deleteclient.py
formance/models/operations/deleteconfig.py
formance/models/operations/deletescope.py
formance/models/operations/deletescopefromclient.py
formance/models/operations/deletesecret.py
formance/models/operations/deletetransientscope.py
formance/models/operations/getaccount.py
formance/models/operations/getbalance.py
formance/models/operations/getbalances.py
formance/models/operations/getbalancesaggregated.py
formance/models/operations/getconnectortask.py
formance/models/operations/getflow.py
formance/models/operations/gethold.py
formance_python_sdk-0.3.1.dist-info/LICENSE.md
formance_python_sdk-0.3.1.dist-info/METADATA
formance_python_sdk-0.3.1.dist-info/WHEEL
formance_python_sdk-0.3.1.dist-info/top_level.txt
formance_python_sdk-0.3.1.dist-info/RECORD
